<profile>

<ReportVersion>
<Version>2018.3</Version>
</ReportVersion>

<UserAssignments>
<unit>ns</unit>
<ProductFamily>zynq</ProductFamily>
<Part>xc7z020clg400-1</Part>
<TopModelName>StreamingMaxPool</TopModelName>
<TargetClockPeriod>5.00</TargetClockPeriod>
<ClockUncertainty>0.62</ClockUncertainty>
</UserAssignments>

<PerformanceEstimates>
<PipelineType>none</PipelineType>
<SummaryOfTimingAnalysis>
<unit>ns</unit>
<EstimatedClockPeriod>4.274</EstimatedClockPeriod>
</SummaryOfTimingAnalysis>
<SummaryOfOverallLatency>
<unit>clock cycles</unit>
<Best-caseLatency>2074</Best-caseLatency>
<Average-caseLatency>2074</Average-caseLatency>
<Worst-caseLatency>2074</Worst-caseLatency>
<Interval-min>2074</Interval-min>
<Interval-max>2074</Interval-max>
</SummaryOfOverallLatency>
<SummaryOfLoopLatency>
<Loop1>
<TripCount>14</TripCount>
<Latency>14</Latency>
<IterationLatency>1</IterationLatency>
</Loop1>
<Loop2>
<TripCount>14</TripCount>
<Latency>2058</Latency>
<IterationLatency>147</IterationLatency>
<Loop2.1>
<TripCount>28</TripCount>
<Latency>113</Latency>
<PipelineII>4</PipelineII>
<PipelineDepth>6</PipelineDepth>
</Loop2.1>
<Loop2.2>
<TripCount>14</TripCount>
<Latency>29</Latency>
<PipelineII>2</PipelineII>
<PipelineDepth>4</PipelineDepth>
</Loop2.2>
</Loop2>
</SummaryOfLoopLatency>
</PerformanceEstimates>

<AreaEstimates>
<Resources>
<BRAM_18K>64</BRAM_18K>
<FF>1149</FF>
<LUT>3900</LUT>
<DSP48E>0</DSP48E>
</Resources>
<AvailableResources>
<BRAM_18K>280</BRAM_18K>
<DSP48E>220</DSP48E>
<FF>106400</FF>
<LUT>53200</LUT>
</AvailableResources>
</AreaEstimates>

<InterfaceSummary>
<RtlPorts>
<name>ap_clk</name>
<Object>StreamingMaxPool</Object>
<Type>return value</Type>
<Scope></Scope>
<IOProtocol>ap_ctrl_hs</IOProtocol>
<IOConfig></IOConfig>
<Dir>in</Dir>
<Bits>1</Bits>
<Attribute>control</Attribute>
</RtlPorts>
<RtlPorts>
<name>ap_rst</name>
<Object>StreamingMaxPool</Object>
<Type>return value</Type>
<Scope></Scope>
<IOProtocol>ap_ctrl_hs</IOProtocol>
<IOConfig></IOConfig>
<Dir>in</Dir>
<Bits>1</Bits>
<Attribute>control</Attribute>
</RtlPorts>
<RtlPorts>
<name>ap_start</name>
<Object>StreamingMaxPool</Object>
<Type>return value</Type>
<Scope></Scope>
<IOProtocol>ap_ctrl_hs</IOProtocol>
<IOConfig></IOConfig>
<Dir>in</Dir>
<Bits>1</Bits>
<Attribute>control</Attribute>
</RtlPorts>
<RtlPorts>
<name>ap_done</name>
<Object>StreamingMaxPool</Object>
<Type>return value</Type>
<Scope></Scope>
<IOProtocol>ap_ctrl_hs</IOProtocol>
<IOConfig></IOConfig>
<Dir>out</Dir>
<Bits>1</Bits>
<Attribute>control</Attribute>
</RtlPorts>
<RtlPorts>
<name>ap_idle</name>
<Object>StreamingMaxPool</Object>
<Type>return value</Type>
<Scope></Scope>
<IOProtocol>ap_ctrl_hs</IOProtocol>
<IOConfig></IOConfig>
<Dir>out</Dir>
<Bits>1</Bits>
<Attribute>control</Attribute>
</RtlPorts>
<RtlPorts>
<name>ap_ready</name>
<Object>StreamingMaxPool</Object>
<Type>return value</Type>
<Scope></Scope>
<IOProtocol>ap_ctrl_hs</IOProtocol>
<IOConfig></IOConfig>
<Dir>out</Dir>
<Bits>1</Bits>
<Attribute>control</Attribute>
</RtlPorts>
<RtlPorts>
<name>in_V_V_dout</name>
<Object>in_V_V</Object>
<Type>pointer</Type>
<Scope></Scope>
<IOProtocol>ap_fifo</IOProtocol>
<IOConfig></IOConfig>
<Dir>in</Dir>
<Bits>64</Bits>
<Attribute>data</Attribute>
</RtlPorts>
<RtlPorts>
<name>in_V_V_empty_n</name>
<Object>in_V_V</Object>
<Type>pointer</Type>
<Scope></Scope>
<IOProtocol>ap_fifo</IOProtocol>
<IOConfig></IOConfig>
<Dir>in</Dir>
<Bits>1</Bits>
<Attribute>control</Attribute>
</RtlPorts>
<RtlPorts>
<name>in_V_V_read</name>
<Object>in_V_V</Object>
<Type>pointer</Type>
<Scope></Scope>
<IOProtocol>ap_fifo</IOProtocol>
<IOConfig></IOConfig>
<Dir>out</Dir>
<Bits>1</Bits>
<Attribute>control</Attribute>
</RtlPorts>
<RtlPorts>
<name>out_V_V_din</name>
<Object>out_V_V</Object>
<Type>pointer</Type>
<Scope></Scope>
<IOProtocol>ap_fifo</IOProtocol>
<IOConfig></IOConfig>
<Dir>out</Dir>
<Bits>64</Bits>
<Attribute>data</Attribute>
</RtlPorts>
<RtlPorts>
<name>out_V_V_full_n</name>
<Object>out_V_V</Object>
<Type>pointer</Type>
<Scope></Scope>
<IOProtocol>ap_fifo</IOProtocol>
<IOConfig></IOConfig>
<Dir>in</Dir>
<Bits>1</Bits>
<Attribute>control</Attribute>
</RtlPorts>
<RtlPorts>
<name>out_V_V_write</name>
<Object>out_V_V</Object>
<Type>pointer</Type>
<Scope></Scope>
<IOProtocol>ap_fifo</IOProtocol>
<IOConfig></IOConfig>
<Dir>out</Dir>
<Bits>1</Bits>
<Attribute>control</Attribute>
</RtlPorts>
</InterfaceSummary>

</profile>
